[{"problem":11,"code":"[:b 2\t]","user":"5372e7d9e4b06d7f452d9e02"},{"problem":11,"code":"(conj {:b 3} {:b 2})","user":"5800b9f0e4b0a837a8b30c43"},{"code":"[:b (- 4 2)]","problem":11,"user":"4e15c301535d04ed9115e7e5"},{"code":"{ :b, 2}","problem":11,"user":"52c1e88ee4b07a9af579236c"},{"code":"{:b (mod 20 18)}","problem":11,"user":"50a024c8e4b08df8156e9e48"},{"problem":11,"code":"{:b 2, :a 1}","user":"5455c2f3e4b080a794c2c87d"},{"problem":11,"code":"(conj {:a 1 :b 2} [:c 3])","user":"5c4790fde4b0e06e1360a3b3"},{"code":"(hash-map :b 2)\n[:b 2]\n{:b 2}","problem":11,"user":"4f871f6ae4b033992c121c57"},{"problem":11,"code":"{:b 2}\n;[:b 2]","user":"5430b3b6e4b0dad94371f2db"},{"code":"[:b 10] [:b 2]","problem":11,"user":"5252d6c7e4b0541d1855b8d4"},{"code":"{:b(+(*)(*))}","problem":11,"user":"53307da1e4b019098a6f8b5e"},{"problem":11,"code":"{:b  2}","user":"55079e55e4b021ccfedb96aa"},{"code":"(vector  :b 2)","problem":11,"user":"50e111f7e4b084616e11c663"},{"code":"{:b 2} [:b 2]","problem":11,"user":"5130795ce4b08c712d3fae38"},{"code":"{:a 1 :b 2}","problem":11,"user":"4fbca2fce4b081705acca2f7"},{"code":";; conj on a hash-map is exactly the same, it goes through KVPair by KVPair, adding them to the hash-map\n[:b 2]","problem":11,"user":"53713ebee4b0fc7073fd6ead"},{"code":"(first '({:b 2} \"Goldilocks\" \"Yo Moma\"))","problem":11,"user":"4e9894ab535dbda64a6f6b5d"},{"problem":11,"code":"{:b (- 42 (+ 10 30))}","user":"57b66a7be4b0fbc9809a27c2"},{"problem":11,"code":"{:b,,,,, 2}","user":"4db863d7535d1e037afb2190"},{"problem":11,"code":"[:b 2] [:a 1] [:c 1]","user":"5cd4c3dae4b0ccb061962925"},{"problem":11,"code":"{:a 1, :b 2, :c 3} {:c 3, :a 1}","user":"58c59c48e4b021aa9917ed3f"},{"problem":11,"code":"{:b,,, 2}","user":"53e2ac1ae4b036ad0777e3f3"},{"code":"; [:b 2]\n{:b 2}","problem":11,"user":"51830c7ae4b0353c468deb78"},{"code":"{:b, 2}","problem":11,"user":"4eb73a75535d7eef30807374"},{"code":"(vec '(:b 2))","problem":11,"user":"4e7dc43a535db169f9c796e7"},{"problem":11,"code":"{:b 2}\n;; [:b 2]","user":"59a5b399e4b066c664927d68"},{"code":"{:a 1, :b 2, :c 3}{:c 3, :a 1}","problem":11,"user":"51dabb76e4b02ceefd947772"},{"code":"[:b 2]","problem":11,"user":"4dd62278535d2dad7130b5c7"},{"code":"{ :b 2}","problem":11,"user":"4ec3893d535dcc7ae8597d58"},{"problem":11,"code":"[:b 2] ;; or {:b 2}","user":"568ead04e4b0dcc4269f40d8"},{"code":"{:a 1, :b 2}","problem":11,"user":"4f24957ae4b0d66497709fed"},{"problem":11,"code":"(or {:b 2} [:b 2])","user":"5515bed5e4b055c2f668d4f0"},{"problem":11,"code":"{:b 2}\n;(vec '(:b 2))","user":"560dfa8de4b05f002753df46"},{"problem":11,"code":"{:b 2,}","user":"5924009ce4b072a2710fce45"},{"code":"{:a 1, :b 2, :c 3}","problem":11,"user":"4f4feb95e4b03ad3f0c10cf0"},{"code":";Map 中的项其实就是一对一对的键值对，添加的时候可以用键值对形式，也可以用向量形式\n;[:b 2]\n{:b 2}","problem":11,"user":"534ab3f5e4b084c2834f4a6e"},{"code":"(vec `(:b 2))","problem":11,"user":"50399468e4b088a6a14ca768"},{"code":"{:b 2}\n[:b 2]","problem":11,"user":"4e580746535d8a8b8723a28c"},{"code":"{:a 1 :b 2 :c 3}","problem":11,"user":"4e6a5238535d8ccf87e9fec9"},{"problem":11,"code":"(vec [:b 2])","user":"5a9306dfe4b0d174b936c716"},{"code":"x","problem":11,"user":"52e635b3e4b09f7907dd146f"},{"problem":11,"code":"{:b 2, :c 2}","user":"5c1a0e64e4b01240ff567205"},{"code":"(vector :b 2)","problem":11,"user":"4ec92a04535d6d7199dd36fa"},{"problem":11,"code":"[:b 2] \n; {:b 2}","user":"5beef257e4b0a6d31fed2137"},{"code":"[:b 2]\n  {:b 2}","problem":11,"user":"4e6dd0f5535d5021c1a895f3"},{"code":"{:b 2, }","problem":11,"user":"525d4159e4b0cb4875a45d66"},{"problem":11,"code":"(set {:b 2})","user":"5606d71ce4b08b23635d317a"},{"problem":11,"code":"{':b 2}","user":"5f77890ae4b02876ed9fd0b9"},{"code":"{:a 1, :b 2, :c 3 }","problem":11,"user":"5153bae8e4b0252ac4b1663c"},{"code":"[:b,2]","problem":11,"user":"50cbc2bbe4b0f78a8e1645bd"},{"code":"[:b, 2]","problem":11,"user":"4fa1d3abe4b0dcca54ed6d63"},{"code":"[:b :2]\n{:b 2}","problem":11,"user":"4fce75cfe4b03432b189f400"},{"problem":11,"code":"{(keyword \"b\") 2}","user":"57bf2aace4b05aa3c4741c73"},{"code":"'[:b 2]","problem":11,"user":"4ddee2d0535d08e6dec9fdda"},{"problem":11,"code":"{:b 2 :c 3 }","user":"55cbd29be4b0e31453f64a0a"},{"code":"{:b,,,,2}","problem":11,"user":"4ef9e7bc535dced4c769f26c"},{"problem":11,"code":"{:b 2, :c 1}","user":"59496129e4b07ddc2dafadd7"},{"problem":11,"code":"{:b 2}\n\n;; can be solved using a vector\n;; [:b 2]","user":"561dd08fe4b064ca9f4b16b7"},{"problem":11,"code":"{:c 3,:b 2, :a 1}","user":"540b8155e4b0addc1aec66f7"},{"problem":11,"code":",{:b 2},","user":"55e46371e4b050e68259b44f"},{"code":"[:b 2] {:b 2} {:a 1}","problem":11,"user":"52f09d3ce4b05e3f0be25ee3"},{"code":"{ :b 2 }","problem":11,"user":"4e234536535d04ed9115e820"},{"code":"{:c 3 :a 1 :b 2}","problem":11,"user":"52a3fabfe4b04e0c58e87c05"},{"problem":11,"code":"[:b   2]","user":"5e5349ebe4b027a2e10ac0e2"},{"code":"[:b  2]","problem":11,"user":"4e39c710535deb9a81d77f45"},{"code":"[(:b {:b :b}) (+ 1 1)]\n;; :p","problem":11,"user":"4e64ae65535d8ccf87e9fe6d"},{"problem":11,"code":"{:b 2}\n{:c 4 :b 2}","user":"5fba387ae4b03f550f44822f"},{"code":"[:a 1] [:b 2]","problem":11,"user":"52299d14e4b04c906c9c6a7e"},{"code":"{:b 2, :a 1}\n; {:b 2,}\n; {:b 2}\n; [:b 2]","problem":11,"user":"516e3cb1e4b0284f4b26df82"},{"code":"(sorted-map :b 2)","problem":11,"user":"51eee71ae4b0871fa145d992"},{"problem":11,"code":"[:b            2]","user":"5567e14ae4b0c656e3ff184b"},{"problem":11,"code":"(conj {:a  1} {:b 2} [:c 3])","user":"594ebd25e4b07ddc2dafaebb"},{"problem":11,"code":"; (hash-map :b 2)\n{ :b 2 }","user":"5ecf3905e4b016b56eae05a4"},{"code":"{:c 3, :b 2, :a 1}","problem":11,"user":"52d80e96e4b09f7907dd1385"},{"problem":11,"code":"[:b 2] [:c 5]","user":"5e28c2a6e4b05b4b015161a3"},{"problem":11,"code":"(let [total {:a 1, :b 2, :c 3}\n      part1 {:a 1}\n      part2 (apply hash-map [:c 3])]\n  (apply dissoc total\n         (apply conj (keys part1)\n               (keys part2))))","user":"5613c76ce4b05f002753dfa7"},{"problem":11,"code":"{:a 1} {:b 2} [:c 3]","user":"5bbcb965e4b0a20761a2362d"},{"code":"{:b 2}\n\n[:b 2]","problem":11,"user":"4e9dd9ab535dbda64a6f6b8d"},{"code":"; [:b 2]\n; {:b 2}\n\n\n; (conj {:a 1} [:b 2])\n(conj (hash-map :a 1) {:a 1} [:b 2])","problem":11,"user":"525f61aae4b0cb4875a45dcb"},{"problem":11,"code":";;{:b 2}\n\n\n(assoc {} (keyword (str (char (int \\b)))) 2)","user":"56ff0ef3e4b08d47c97781ba"},{"code":"[:b (+ 1 1)]","problem":11,"user":"4fe610fde4b0e8f79898fece"},{"code":"(conj {} [:b 2] [:b 2])","problem":11,"user":"5391fa0de4b0b51d73faaead"},{"code":"(hash-map :b 2)","problem":11,"user":"4e3a2761535deb9a81d77f48"},{"problem":11,"code":"{:b 2} [:a 1]","user":"56f258d3e4b04a395b9a04a1"},{"problem":11,"code":"(conj {:a 1} {:b 2})","user":"53c39a9ae4b00fb29b22127d"},{"problem":11,"code":"{:a 1,:c 3,:b 2}","user":"5c0614f6e4b0bdcf453d16a9"},{"code":"{:b 2\n}","problem":11,"user":"508ae5a2e4b0be79e5b189be"},{"code":"[\n:b 2]","problem":11,"user":"509d528de4b0bb99d6371049"},{"code":"[:b 2   ]","problem":11,"user":"51a3a976e4b0e77c4ca60bf5"},{"code":"[:b 2] [:c 3]","problem":11,"user":"4fb5a72ee4b081705acca2c2"},{"code":"{:b 2}","problem":11,"user":"4dd61f98535d2dad7130b5c6"},{"problem":11,"code":"[:b 2\n ]","user":"54b567eee4b05787c3b163a2"},{"problem":11,"code":"[':b 2]","user":"6001ea38e4b074f607df662a"},{"code":"(conj [:b] 2)","problem":11,"user":"51ab1da1e4b04e3dc0c27b30"},{"code":"[ :b 2 ]","problem":11,"user":"4e352362535deb9a81d77f2c"},{"problem":11,"code":"`[:b 2]","user":"56bdd003e4b0f26550335976"},{"code":"[:b 2] [:a 1]","problem":11,"user":"5368ffa2e4b0243289761e94"},{"problem":11,"code":"{:b 2 :c 4}","user":"55dac0dfe4b0e31453f64adb"},{"code":"(conj {:a 1} [:c 3] [:b 2])","problem":11,"user":"4fc7ddffe4b0ee37620e182b"},{"code":"{:b 2, :c 3, :a 1}","problem":11,"user":"4f067029535dcb61093f6c12"},{"problem":11,"code":"{:a 1, :b 2, :c 3}{:a 1, :c 3}","user":"5ed5a0dce4b016b56eae05d7"},{"code":"{:b 2 :c 3}","problem":11,"user":"4da8dd6e30acd6ed12482a68"},{"problem":11,"code":"{:a 1} [:b 2]","user":"57d9200ee4b0bd073c2023f7"},{"code":"[:b 2] [:c 3] [:a 1]","problem":11,"user":"4fb0a1e0e4b081705acca269"},{"problem":11,"code":"(vector :b 2 )","user":"5832be57e4b089d5ab817c86"},{"code":"[:b 2\n]","problem":11,"user":"52f2e4cce4b05e3f0be25f01"},{"code":"{:b 2, :c 3}","problem":11,"user":"4ff2430ae4b0678c553fc336"},{"problem":11,"code":"(conj {:a 1 :b 2 :c 3} {:a 1} [:c 3])","user":"5df3b8a2e4b03c219ef1a36e"},{"problem":11,"code":"{\n  :b 2}","user":"5610d39de4b05f002753df75"},{"problem":11,"code":"{:b 2} [:b 2] {:b 2 :c 3}","user":"58dd8d39e4b0a4d5acaab6d1"},{"code":"(conj {:a 1} [:b 2] [:c 3])","problem":11,"user":"528ec5b8e4b0239c8a67aee8"},{"code":"(conj {:a 1} {:b 2} [:c 3])","problem":11,"user":"51ad808ee4b09397d5109784"},{"problem":11,"code":";; skill: Construct a map by conjoining vectors or maps of key-value pairs with the `conj` function\n;; note: this does NOT work: '(:b 2)\n;; note: this DOES work: [:b 2]\n{:b 2}","user":"60917abde4b00e9e6653c3d5"},{"problem":11,"code":"{:a 1, :c 3, :b 2}","user":"560d2bf5e4b05f002753df39"},{"problem":11,"code":"(clojure.lang.MapEntry. :b 2)","user":"5518df4ce4b06a49daca83ce"},{"code":"[ :b 2]","problem":11,"user":"4f8801d3e4b033992c121c5e"},{"problem":11,"code":"[:a 5] [:b 2] [:a 1]","user":"541adefbe4b01498b1a71a5f"},{"problem":11,"code":"{:b 2} {:c 3}","user":"5b37fd11e4b02d533a91bbac"},{"code":"; {:b 2}\n [:b 2]","problem":11,"user":"52df4198e4b09f7907dd13fe"},{"code":"{:b ({:a (+ 1 1)} :a)}","problem":11,"user":"52ea5e0ae4b09f7907dd14bc"},{"code":"[:b 2,]","problem":11,"user":"5072d016e4b0e3170b5a8691"},{"problem":11,"code":"{:b 2 :a 1 :c 3}","user":"56a75810e4b0542e1f8d14fc"},{"code":"[:b 2 ]","problem":11,"user":"4f83ee95e4b033992c121c26"},{"code":"{:b 2 :a 1}","problem":11,"user":"4fea119ae4b0547ebccb2488"},{"problem":11,"code":"#_{:b 2}\n(first (map identity {:b 2}))","user":"5c1c08cde4b01240ff567219"},{"problem":11,"code":"(array-map :b 2)","user":"54d412e2e4b0a52adc2e1ffe"},{"code":"(:b (hash-map :b [:b 2]))","problem":11,"user":"4ff73b7ae4b0678c553fc38c"},{"code":"{:b 2 }","problem":11,"user":"4ef78a80535dced4c769f255"},{"problem":11,"code":"[:b 2]\n{:b 2}","user":"5446158ce4b032a45b8693a6"},{"problem":11,"code":"(conj {:a 1} {:b 2} {:c 3})","user":"5508b405e4b06e50f9beb110"},{"code":"'{:b 2}","problem":11,"user":"4ddbf54e535d02782fcbe9ff"},{"code":"(vec (list :b 2))","problem":11,"user":"4ec132a0535dfed6da9c6da9"},{"code":"(hash-map :b, 2)","problem":11,"user":"4ebc7b39535dfed6da9c6d85"},{"problem":11,"code":"{:b 2}\n(:b 2)\n[:b 2]","user":"55f04526e4b06e875b46ce20"},{"problem":11,"code":"{:b , 2}","user":"59caaa41e4b0a024fb6ae59f"},{"problem":11,"code":"(vec (list :b\n   2))","user":"5703b4f2e4b08d47c97781f5"}]