[{"problem":162,"code":"(if \"great\" 1 0)","user":"584278e1e4b089d5ab817e19"},{"code":"(if (> (compare \"money\" \"bitches\") 0) 1 0)","problem":162,"user":"53224d45e4b09d4e7a9b54c0"},{"code":"1\n1\n1\n1\n1\n1\n1","problem":162,"user":"4fead955e4b0140c20fb9c10"},{"problem":162,"code":"(if\n   (first\n   \t\t\t (str\n     (- (/ (+ 3.14\n             \t\t\t\t (* 55 (count\n                     ( take-while\n                       #(> 10 %)(range))))) 72) \n        6.6825)))  \n   \t\t\t\t\t\t\t\t\t\t\t\t(- (* 5 (/ 2 1) 9) 89 )    )","user":"56ede653e4b04a395b9a0449"},{"code":"(count '(1))","problem":162,"user":"51502056e4b098b221effc25"},{"code":"(bit-not -2)","problem":162,"user":"4e49badd535dc968683fc4c9"},{"code":"({:uno 1} :uno)","problem":162,"user":"50d4c626e4b09cc622d65a70"},{"problem":162,"code":"(/ (- 5 3) 2) ; Aha! Original solution!","user":"575ef4b6e4b08062f99a4e78"},{"code":"(first [1 1])","problem":162,"user":"51ab70c3e4b04e3dc0c27b33"},{"code":"(apply + (take 2 (range 3)))","problem":162,"user":"51bee4afe4b013aa0d74b809"},{"problem":162,"code":"(if 0 1 0)","user":"55eeeb81e4b0121d4835fdf7"},{"code":"1 1 1 1 1","problem":162,"user":"53973e7be4b0b51d73faaee6"},{"problem":162,"code":"(-> (reduce + (range -10 10)) str reverse second str Integer.)","user":"544285dde4b032a45b869380"},{"code":"1\n(if nil 0 1)\n(if false 0 1)\n(if 0 1 0)\n(when 1 1)\n(when-not false 1)\n(when-not nil 1)\n(when (not nil) 1)\n(when (not false) 1)\n(when (not (not true)) 1)","problem":162,"user":"500ae2ade4b03d00572d2d7d"},{"code":"((fn lolol [] 1))","problem":162,"user":"4e8dd6cb535d65386fec213b"},{"problem":162,"code":"(inc 0)","user":"53cd66dee4b00fb29b2212e2"},{"code":"(first (shuffle (filter #(= % (/ % %)) (range 1 1000))))","problem":162,"user":"512f06c5e4b0762be4c7aad7"},{"problem":162,"code":"(- (int (first (seq (str 1)))) (int (first (seq (str 0)))))","user":"594c1baae4b07ddc2dafae59"},{"problem":162,"code":"(first [1 2])","user":"60ae0ac5e4b00e9e6653c495"},{"problem":162,"code":"1 1 1 1 1 1 1","user":"570d4c30e4b0b0fb43fd06da"},{"problem":162,"code":"(->> 1000\n     (range 1)\n     first)","user":"5579bc24e4b05c286339e098"},{"code":"(- 2 1)","problem":162,"user":"5097c837e4b00ad8bab4e973"},{"problem":162,"code":"(+ 1 (* 0 (+ 3 5 6) (* 2 5)))","user":"4fe8ddafe4b0547ebccb242c"},{"problem":162,"code":"(* 1 1)","user":"5fc3850de4b0db0e95a5f3fd"},{"code":"(if-not false 1 0)","problem":162,"user":"4fb36281e4b081705acca29d"},{"problem":162,"code":"(- 5 4)","user":"558b50d5e4b027778923762b"},{"problem":162,"code":"((identity (constantly 1)) 9001)","user":"55ab07e0e4b0988bba2ad953"},{"problem":162,"code":"'1","user":"54e396f1e4b024c67c0cf7de"},{"problem":162,"code":"(/ 10 10)","user":"55fc07d3e4b0f488688e066e"},{"code":"(reduce * 1 (repeat 500 1))","problem":162,"user":"4dafa380edd6309eace4d17c"},{"problem":162,"code":"((fn[](if (zero? 0) 1 0)))","user":"50e896a5e4b0ebbe794eb7eb"},{"code":"(*)","problem":162,"user":"4e7dfab0535db169f9c796f9"},{"code":"(+ (+ (+ (+ (+ 1 -1) (+ 4 2)) 3) 6) -14)","problem":162,"user":"527c0509e4b03e8d9a4a75aa"},{"problem":162,"code":"(first [1 2 3])","user":"580d7bdae4b0849f6811b73c"},{"code":"(identity 1)","problem":162,"user":"4f49108ae4b0d56e7bb92be5"},{"problem":162,"code":"(last (reverse (range 1 1000 1)))","user":"603ae21de4b0d5df2af222fb"},{"problem":162,"code":"(- 1001 1000)","user":"55079757e4b021ccfedb96a9"},{"problem":162,"code":"(if true 1 0)","user":"5f0824c5e4b0cf489e8d7f5b"},{"code":"1/1","problem":162,"user":"4db858d1535d1e037afb218c"},{"code":"(+ 0 1)","problem":162,"user":"5125d963e4b05d10e3e395fe"},{"problem":162,"code":"(- 3 2)","user":"58247423e4b051871117bec5"},{"code":"(if nil 0 1)","problem":162,"user":"4dadca03c9a9d6ed4199dc57"},{"code":"1","problem":162,"user":"4da3e51330acd6ed10482a68"},{"problem":162,"code":"(and (:major *clojure-version*) \n     (if (not= nil false) 1 0)\n     (- (:minor *clojure-version*) 3))","user":"55b22c33e4b0da326a65cf79"},{"problem":162,"code":"(dec 2) ;; haha","user":"5564c113e4b0c656e3ff180d"},{"problem":162,"code":"(+ (*) (+))","user":"4e836a06535db62dc21a62d5"},{"problem":162,"code":"1\n1\n1\n1\n1\n1","user":"5fff510de4b074f607df6608"},{"problem":162,"code":"1\n1\n1","user":"52c0876de4b07a9af579234f"},{"problem":162,"code":"( second (range))","user":"556880dae4b0c656e3ff1856"},{"code":"(- 43 42)","problem":162,"user":"4fde1109e4b05e33b9224f81"},{"problem":162,"code":"1 1","user":"5653600ce4b0f9d632dd8471"},{"code":"(/ (+ 1 1) 2)","problem":162,"user":"4e3ac1b2535deb9a81d77f4c"},{"code":"(or 1 0)","problem":162,"user":"51a89810e4b08d8ec191b817"},{"problem":162,"code":"; 1 for TRUE, 0 for FALSE\n; false and nil are logical false\n\n1","user":"57c44053e4b05aa3c4741ccb"},{"problem":162,"code":"; de 3e was voor mij duidelijk, if true 1 anders 0\n; de 1 na laatste, als false dan 1 anders 0\n1","user":"5637bd38e4b0bfe05bf117de"},{"code":"(if 1 1 0)","problem":162,"user":"50d20c28e4b05a71a896ef5d"}]